xputer/__init__.py
xputer/__main__.py
xputer/gui.py
xputer/main.py
xputer-0.2.0.dist-info/LICENSE
xputer-0.2.0.dist-info/METADATA
xputer-0.2.0.dist-info/WHEEL
xputer-0.2.0.dist-info/top_level.txt
xputer-0.2.0.dist-info/RECORD
